alibabacloud_secretsmanager_client_v2/__init__.py
alibabacloud_secretsmanager_client_v2/cache_client_builder.py
alibabacloud_secretsmanager_client_v2/secret_manager_cache_client.py
alibabacloud_secretsmanager_client_v2/secret_manager_cache_client_builder.py
alibabacloud_secretsmanager_client_v2/ca/__init__.py
alibabacloud_secretsmanager_client_v2/ca/bj.pem
alibabacloud_secretsmanager_client_v2/ca/bjf.pem
alibabacloud_secretsmanager_client_v2/ca/cd.pem
alibabacloud_secretsmanager_client_v2/ca/de.pem
alibabacloud_secretsmanager_client_v2/ca/gb.pem
alibabacloud_secretsmanager_client_v2/ca/gz.pem
alibabacloud_secretsmanager_client_v2/ca/hhht.pem
alibabacloud_secretsmanager_client_v2/ca/hk.pem
alibabacloud_secretsmanager_client_v2/ca/hy.pem
alibabacloud_secretsmanager_client_v2/ca/hya.pem
alibabacloud_secretsmanager_client_v2/ca/hz.pem
alibabacloud_secretsmanager_client_v2/ca/id.pem
alibabacloud_secretsmanager_client_v2/ca/jp.pem
alibabacloud_secretsmanager_client_v2/ca/mec.pem
alibabacloud_secretsmanager_client_v2/ca/my.pem
alibabacloud_secretsmanager_client_v2/ca/php.pem
alibabacloud_secretsmanager_client_v2/ca/pre_env.pem
alibabacloud_secretsmanager_client_v2/ca/qd.pem
alibabacloud_secretsmanager_client_v2/ca/sgp.pem
alibabacloud_secretsmanager_client_v2/ca/sh.pem
alibabacloud_secretsmanager_client_v2/ca/shf.pem
alibabacloud_secretsmanager_client_v2/ca/sz.pem
alibabacloud_secretsmanager_client_v2/ca/tha.pem
alibabacloud_secretsmanager_client_v2/ca/usf.pem
alibabacloud_secretsmanager_client_v2/ca/usv.pem
alibabacloud_secretsmanager_client_v2/ca/wlcb.pem
alibabacloud_secretsmanager_client_v2/ca/zjk.pem
alibabacloud_secretsmanager_client_v2/cache/__init__.py
alibabacloud_secretsmanager_client_v2/cache/cache_secret_store_strategy.py
alibabacloud_secretsmanager_client_v2/cache/default_secret_cache_hook.py
alibabacloud_secretsmanager_client_v2/cache/file_cache_secret_store_strategy.py
alibabacloud_secretsmanager_client_v2/cache/memory_cache_secret_store_strategy.py
alibabacloud_secretsmanager_client_v2-2.0.0.dist-info/LICENSE
alibabacloud_secretsmanager_client_v2-2.0.0.dist-info/METADATA
alibabacloud_secretsmanager_client_v2-2.0.0.dist-info/WHEEL
alibabacloud_secretsmanager_client_v2-2.0.0.dist-info/top_level.txt
alibabacloud_secretsmanager_client_v2-2.0.0.dist-info/RECORD
