Metadata-Version: 2.1
Name: alibabacloud-secretsmanager-client-v2
Version: 2.0.0
Summary: Alibaba Cloud Secrets Manager Client V2 implementation for Python
Home-page: https://www.alibabacloud.com/
Author: Alibaba Cloud
Maintainer: Alibaba Cloud
License: Apache License 2.0
Keywords: alibabacloud,kms,secretsmanager,secrets,v2
Classifier: Development Status :: 5 - Production/Stable
Classifier: Intended Audience :: Developers
Classifier: License :: OSI Approved :: Apache Software License
Classifier: Programming Language :: Python :: 3
Classifier: Programming Language :: Python :: 3.7
Classifier: Programming Language :: Python :: 3.8
Classifier: Programming Language :: Python :: 3.9
Classifier: Programming Language :: Python :: 3.10
Classifier: Programming Language :: Python :: 3.11
Classifier: Programming Language :: Python :: 3.12
Classifier: Programming Language :: Python :: Implementation :: CPython
Classifier: Topic :: Security
Classifier: Topic :: Security :: Cryptography
Classifier: Topic :: Software Development :: Libraries :: Python Modules
Classifier: Operating System :: OS Independent
Requires-Python: >=3.7
License-File: LICENSE
Requires-Dist: alibabacloud-kms20160120 (>=2.3.1)
Requires-Dist: apscheduler (>=3.5.2)
Requires-Dist: bytebuffer (>=0.1.0)
Requires-Dist: cryptography (>=3.2.1)
